bumbag/__init__.py
bumbag/core.py
bumbag/io.py
bumbag/math.py
bumbag/random.py
bumbag/string.py
bumbag/time.py
bumbag-5.2.1.dist-info/LICENSE
bumbag-5.2.1.dist-info/WHEEL
bumbag-5.2.1.dist-info/METADATA
bumbag-5.2.1.dist-info/LICENSES/DATEUTIL_LICENSE
bumbag-5.2.1.dist-info/LICENSES/TOOLZ_LICENSE
bumbag-5.2.1.dist-info/RECORD
