Metadata-Version: 2.1
Name: bumbag
Version: 5.2.1
Summary: A package for Python utility functions.
Home-page: https://github.com/estripling/bumbag
License: BSD-3-Clause
Keywords: utility functions,bumbag
Author: BumBag Developers
Requires-Python: >=3.8,<4.0
Classifier: License :: OSI Approved :: BSD License
Classifier: Programming Language :: Python :: 3
Classifier: Programming Language :: Python :: 3.8
Classifier: Programming Language :: Python :: 3.9
Classifier: Programming Language :: Python :: 3.10
Classifier: Programming Language :: Python :: 3.11
Classifier: Programming Language :: Python :: 3.10
Classifier: Programming Language :: Python :: 3.8
Classifier: Programming Language :: Python :: 3.9
Classifier: Topic :: Utilities
Requires-Dist: python-dateutil (>=2.8.2,<3.0.0)
Requires-Dist: toolz (>=0.12.0,<0.13.0)
Project-URL: Documentation, https://bumbag.readthedocs.io/en/stable/
Project-URL: Repository, https://github.com/estripling/bumbag
